MANIFEST.in
README.md
setup.py
nyamuk/__init__.py
nyamuk/base_nyamuk.py
nyamuk/event.py
nyamuk/mqtt_pkt.py
nyamuk/nyamuk.py
nyamuk/nyamuk_const.py
nyamuk/nyamuk_msg.py
nyamuk/nyamuk_net.py
nyamuk/utils.py
nyamuk.egg-info/PKG-INFO
nyamuk.egg-info/SOURCES.txt
nyamuk.egg-info/dependency_links.txt
nyamuk.egg-info/top_level.txt
test/pubnya.py
test/simple_publish.py
test/simple_subscribe.py
test/subnya.py