Metadata-Version: 1.0
Name: nyamuk
Version: 0.2.0
Summary: Python MQTT Client Library
Home-page: https://github.com/iwanbk/nyamuk
Author: Iwan Budi Kusnanto
Author-email: iwan.b.kusnanto@gmail.com
License: BSD
Platform: UNKNOWN
